jackal/__init__.py
jackal/__version__.py
jackal/apps.py
jackal/consts.py
jackal/exceptions.py
jackal/expressions.py
jackal/fields.py
jackal/filters.py
jackal/helpers/__init__.py
jackal/helpers/data_helper.py
jackal/helpers/math_helper.py
jackal/inspectors.py
jackal/loaders.py
jackal/management/__init__.py
jackal/management/commands/__init__.py
jackal/management/commands/create_app.py
jackal/managers.py
jackal/mixins/__init__.py
jackal/mixins/bind_mixin.py
jackal/models.py
jackal/paginators.py
jackal/permissions.py
jackal/serializers.py
jackal/settings.py
jackal/shortcuts.py
jackal/structures.py
jackal/tests.py
jackal/views/__init__.py
jackal/views/base.py
jackal/views/generics.py
django_jackal-3.0.3.dist-info/LICENSE
django_jackal-3.0.3.dist-info/WHEEL
django_jackal-3.0.3.dist-info/METADATA
django_jackal-3.0.3.dist-info/RECORD
